{
  "name": "images",
  "endpoints": [
    {
      "method": "POST",
      "path": "/images",
      "body": {
        "upload": "image"
      }
    },
    {
      "method": "GET",
      "path": "/images",
      "query": {
        "offset": "number",
        "limit": "number",
        "sort": "string",
        "query": "string",
        "showInactive": "string"
      }
    },
    {
      "method": "GET",
      "path": "/images/:id",
      "params": {
        "id": "string"
      }
    },
    {
      "method": "DELETE",
      "path": "/images/:id",
      "params": {
        "id": "string"
      }
    },
    {
      "method": "GET",
      "path": "/images/download/:id",
      "params": {
        "id": "string"
      },
      "download": true
    }
  ]
}